Workbook

Sheet Resumen
A1: CiberHome · Resumen de la base de datos
A2: Se calcula solo a partir de las hojas Pedidos, Lineas y Cuentas (primeras 5000 filas).
A3: Indicador | B3: Valor
A4: Pedidos totales | B4: =COUNTA(Pedidos!B2:B5000) -> 0
A5: Ingresos totales (€) | B5: =SUM(Pedidos!S2:S5000) -> 0
A6: Ticket medio (€) | B6: =IF(B4=0,0,B5/B4) -> 0
A7: Descuentos concedidos (€) | B7: =SUM(Pedidos!Q2:Q5000) -> 0
A8: Ingresos por instalación (€) | B8: =SUM(Pedidos!P2:P5000) -> 0
A9: Pedidos con envío a domicilio | B9: =COUNTIF(Pedidos!L2:L5000,"Envío a domicilio") -> 0
A10: Pedidos con recogida en tienda | B10: =COUNTIF(Pedidos!L2:L5000,"Recogida en tienda") -> 0
A11: Pedidos con instalación | B11: =COUNTIF(Pedidos!N2:N5000,"Sí") -> 0
A12: Pagos con Stripe | B12: =COUNTIF(Pedidos!K2:K5000,"Stripe") -> 0
A13: Pagos con PayPal | B13: =COUNTIF(Pedidos!K2:K5000,"PayPal") -> 0
A14: Cuentas registradas | B14: =COUNTA(Cuentas!A2:A5000) -> 0
A15: Unidades vendidas | B15: =SUM(Lineas!E2:E5000) -> 0
A17: Ventas por producto
A18: ID producto | B18: Producto | C18: Precio base (€) | D18: Unidades vendidas | E18: Ingresos (€)
A19: cam1 | B19: Cámara exterior HD | C19: 79 | D19: =SUMIF(Lineas!$C$2:$C$5000,A19,Lineas!$E$2:$E$5000) -> 0 | E19: =SUMIF(Lineas!$C$2:$C$5000,A19,Lineas!$F$2:$F$5000) -> 0
A20: cerr1 | B20: Cerradura inteligente | C20: 129 | D20: =SUMIF(Lineas!$C$2:$C$5000,A20,Lineas!$E$2:$E$5000) -> 0 | E20: =SUMIF(Lineas!$C$2:$C$5000,A20,Lineas!$F$2:$F$5000) -> 0
A21: rob1 | B21: Robot aspirador | C21: 249 | D21: =SUMIF(Lineas!$C$2:$C$5000,A21,Lineas!$E$2:$E$5000) -> 0 | E21: =SUMIF(Lineas!$C$2:$C$5000,A21,Lineas!$F$2:$F$5000) -> 0
A22: asis1 | B22: Altavoz asistente inteligente | C22: 59 | D22: =SUMIF(Lineas!$C$2:$C$5000,A22,Lineas!$E$2:$E$5000) -> 0 | E22: =SUMIF(Lineas!$C$2:$C$5000,A22,Lineas!$F$2:$F$5000) -> 0
A23: bomb1 | B23: Bombillas inteligentes (pack 3) | C23: 39 | D23: =SUMIF(Lineas!$C$2:$C$5000,A23,Lineas!$E$2:$E$5000) -> 0 | E23: =SUMIF(Lineas!$C$2:$C$5000,A23,Lineas!$F$2:$F$5000) -> 0
A24: term1 | B24: Termostato inteligente | C24: 119 | D24: =SUMIF(Lineas!$C$2:$C$5000,A24,Lineas!$E$2:$E$5000) -> 0 | E24: =SUMIF(Lineas!$C$2:$C$5000,A24,Lineas!$F$2:$F$5000) -> 0
A25: acc-panel-cam1 | B25: Panel solar para cámara | C25: 19 | D25: =SUMIF(Lineas!$C$2:$C$5000,A25,Lineas!$E$2:$E$5000) -> 0 | E25: =SUMIF(Lineas!$C$2:$C$5000,A25,Lineas!$F$2:$F$5000) -> 0
A26: acc-soporte-cam1 | B26: Soporte de pared orientable | C26: 9 | D26: =SUMIF(Lineas!$C$2:$C$5000,A26,Lineas!$E$2:$E$5000) -> 0 | E26: =SUMIF(Lineas!$C$2:$C$5000,A26,Lineas!$F$2:$F$5000) -> 0
A27: acc-filtro-rob1 | B27: Filtro HEPA de repuesto | C27: 15 | D27: =SUMIF(Lineas!$C$2:$C$5000,A27,Lineas!$E$2:$E$5000) -> 0 | E27: =SUMIF(Lineas!$C$2:$C$5000,A27,Lineas!$F$2:$F$5000) -> 0
A28: acc-base-rob1 | B28: Base de carga y vaciado automático | C28: 89 | D28: =SUMIF(Lineas!$C$2:$C$5000,A28,Lineas!$E$2:$E$5000) -> 0 | E28: =SUMIF(Lineas!$C$2:$C$5000,A28,Lineas!$F$2:$F$5000) -> 0
A29: Total | D29: =SUM(D19:D28) -> 0 | E29: =SUM(E19:E28) -> 0
A31: Nota: el catálogo y los precios base están copiados de la web (campo en azul = editable). Si añades un producto en la web, añade una fila aquí.

Sheet Pedidos
A1: Fecha | B1: Nº pedido | C1: Usuario | D1: Email | E1: Nombre | F1: Apellidos | G1: Teléfono | H1: Dirección | I1: CP | J1: Ciudad | K1: Método de pago | L1: Entrega | M1: Tienda de recogida | N1: Instalación | O1: Subtotal (€) | P1: Instalación (€) | Q1: Descuento (€) | R1: Código promo | S1: Total (€) | T1: Nº productos | U1: Productos

Sheet Lineas
A1: Fecha | B1: Nº pedido | C1: ID producto | D1: Producto | E1: Cantidad | F1: Total línea (€)

Sheet Cuentas
A1: Usuario | B1: Email | C1: Nombre | D1: Método de acceso | E1: Fecha de alta | F1: Último acceso | G1: Nº accesos | H1: País | I1: Ciudad

Sheet Instrucciones
A1: Cómo usar este Excel
A3: 1. Las hojas Pedidos, Lineas y Cuentas tienen filtro en TODAS las columnas (flechita de la cabecera). Pulsa Ctrl+Mayús+L para quitarlo o ponerlo.
A4: 2. Esta plantilla está vacía a propósito: los datos reales los escribe la web sola en tu Google Sheet cuando alguien compra o crea una cuenta.
A5: 3. Para filtrar en Excel con datos reales: abre tu Google Sheet → Archivo → Descargar → Microsoft Excel (.xlsx). Tendrá el mismo orden de columnas.
A6: 4. Si prefieres usar esta plantilla: súbela a Google Drive y ábrela como Hoja de cálculo de Google; así tendrás las hojas ya preparadas.
A7: 5. La hoja Resumen se calcula sola con fórmulas. No escribas encima de las celdas con fórmulas.
A8: 6. Cada fila de Pedidos es un pedido; la hoja Lineas tiene una fila por producto del pedido (une ambas por «Nº pedido»).
A10: Ejemplo de cómo se ve una fila de la hoja Pedidos (solo ilustrativo, no cuenta en el Resumen):
A11: Fecha | B11: Nº pedido | C11: Usuario | D11: Email | E11: Nombre | F11: Apellidos | G11: Teléfono | H11: Dirección | I11: CP | J11: Ciudad | K11: Método de pago | L11: Entrega | M11: Tienda de recogida | N11: Instalación | O11: Subtotal (€) | P11: Instalación (€) | Q11: Descuento (€) | R11: Código promo | S11: Total (€) | T11: Nº productos | U11: Productos
A12: 09/10/2026 12:30 | B12: DOM-261009-AB12 | C12: ana | D12: ana@correo.es | E12: Ana | F12: Pérez | G12: 600112233 | H12: Calle Mayor 1 | I12: 28001 | J12: Madrid | K12: Stripe | L12: Envío a domicilio | N12: Sí | O12: 269 | P12: 29 | Q12: 26.9 | R12: BIENVENIDO10 | S12: 271.1 | T12: 3 | U12: 2 × Cámara exterior HD; 1 × Termostato inteligente
